mono_cbp/__init__.py
mono_cbp/cli.py
mono_cbp/config/__init__.py
mono_cbp/config/defaults.py
mono_cbp/eclipse_masking/__init__.py
mono_cbp/eclipse_masking/masker.py
mono_cbp/injection_retrieval/__init__.py
mono_cbp/injection_retrieval/injector.py
mono_cbp/model_comparison/__init__.py
mono_cbp/model_comparison/comparator.py
mono_cbp/pipeline/__init__.py
mono_cbp/pipeline/pipeline.py
mono_cbp/transit_finding/__init__.py
mono_cbp/transit_finding/finder.py
mono_cbp/utils/__init__.py
mono_cbp/utils/common.py
mono_cbp/utils/data.py
mono_cbp/utils/detrending.py
mono_cbp/utils/eclipses.py
mono_cbp/utils/monofind.py
mono_cbp/utils/plotting.py
mono_cbp/utils/transit_models.py
mono_cbp-0.1.4.dist-info/licenses/LICENSE
mono_cbp-0.1.4.dist-info/METADATA
mono_cbp-0.1.4.dist-info/WHEEL
mono_cbp-0.1.4.dist-info/entry_points.txt
mono_cbp-0.1.4.dist-info/top_level.txt
mono_cbp-0.1.4.dist-info/RECORD
