Metadata-Version: 2.4
Name: mono-cbp
Version: 0.1.4
Summary: Pipeline for detecting circumbinary planets in TESS light curves
Author-email: Benjamin Davies <ben.d.r.davies@warwick.ac.uk>
License-Expression: GPL-3.0
Project-URL: Homepage, https://github.com/bdrdavies/mono-cbp
Project-URL: Repository, https://github.com/bdrdavies/mono-cbp
Classifier: Development Status :: 4 - Beta
Classifier: Intended Audience :: Science/Research
Classifier: Topic :: Scientific/Engineering :: Astronomy
Classifier: Programming Language :: Python :: 3
Classifier: Programming Language :: Python :: 3.8
Classifier: Programming Language :: Python :: 3.9
Classifier: Programming Language :: Python :: 3.10
Classifier: Programming Language :: Python :: 3.11
Requires-Python: >=3.8
License-File: LICENSE
Requires-Dist: numpy>=1.20.0
Requires-Dist: pandas>=1.3.0
Requires-Dist: matplotlib>=3.4.0
Requires-Dist: scipy<1.13.0,>=1.7.0
Requires-Dist: astropy>=4.3.0
Requires-Dist: lightkurve>=2.0.0
Requires-Dist: pymc==5.12.0
Requires-Dist: arviz==0.17.1
Requires-Dist: bokeh<3.4.0,>=3.1.0
Requires-Dist: exoplanet>=0.5.0
Requires-Dist: exoplanet_core>=0.3.0
Requires-Dist: pytensor==2.19.0
Requires-Dist: wotan>=1.10.0
Requires-Dist: ipykernel>=6.0.0
Requires-Dist: oktopus>=0.1.2
Requires-Dist: autograd>=1.8.0
Requires-Dist: pygam>=0.8.0
Requires-Dist: notebook>=6.0.0
Dynamic: license-file
